[
  { "v1": 12, "v2": 34, "v3": 60, "v4": 80, "v5": 20, "v6": 10 },
  { "v1": 45, "v2": 23, "v3": 30, "v4": 50, "v5": 60, "v6": 70 },
  { "v1": 78, "v2": 56, "v3": 10, "v4": 90, "v5": 40, "v6": 30 },
  { "v1": 34, "v2": 12, "v3": 90, "v4": 20, "v5": 50, "v6": 60 },
  { "v1": 55, "v2": 88, "v3": 25, "v4": 15, "v5": 75, "v6": 45 },
  { "v1": 90, "v2": 70, "v3": 15, "v4": 35, "v5": 85, "v6": 20 },
  { "v1": 22, "v2": 44, "v3": 55, "v4": 65, "v5": 35, "v6": 75 },
  { "v1": 66, "v2": 33, "v3": 70, "v4": 40, "v5": 10, "v6": 50 },
  { "v1": 11, "v2": 99, "v3": 45, "v4": 60, "v5": 95, "v6": 80 },
  { "v1": 38, "v2": 18, "v3": 80, "v4": 25, "v5": 65, "v6": 55 }
]
